jupyterlab_proxy_launcher_command_extension/__init__.py
jupyterlab_proxy_launcher_command_extension/_version.py
jupyterlab_proxy_launcher_command_extension-1.0.14.data/data/share/jupyter/labextensions/jupyterlab_proxy_launcher_command_extension/package.json
jupyterlab_proxy_launcher_command_extension-1.0.14.data/data/share/jupyter/labextensions/jupyterlab_proxy_launcher_command_extension/static/509.de255d2195ed8f3efde6.js
jupyterlab_proxy_launcher_command_extension-1.0.14.data/data/share/jupyter/labextensions/jupyterlab_proxy_launcher_command_extension/static/728.c3bc559a6ff464afc88e.js
jupyterlab_proxy_launcher_command_extension-1.0.14.data/data/share/jupyter/labextensions/jupyterlab_proxy_launcher_command_extension/static/remoteEntry.4ede842322d4486faae1.js
jupyterlab_proxy_launcher_command_extension-1.0.14.data/data/share/jupyter/labextensions/jupyterlab_proxy_launcher_command_extension/static/style.js
jupyterlab_proxy_launcher_command_extension-1.0.14.data/data/share/jupyter/labextensions/jupyterlab_proxy_launcher_command_extension/static/third-party-licenses.json
jupyterlab_proxy_launcher_command_extension-1.0.14.data/data/share/jupyter/labextensions/jupyterlab_proxy_launcher_command_extension/install.json
jupyterlab_proxy_launcher_command_extension-1.0.14.dist-info/METADATA
jupyterlab_proxy_launcher_command_extension-1.0.14.dist-info/WHEEL
jupyterlab_proxy_launcher_command_extension-1.0.14.dist-info/licenses/LICENSE
jupyterlab_proxy_launcher_command_extension-1.0.14.dist-info/RECORD
